{
    "indicator": "Victims of intentional homicide (other perpetrator known to the victim, Male, all ages)",
    "countryData": [
        {
            "Alpha-3 code": "ARE",
            "Country or Area": "UAE",
            "data": [
                {
                    "year": 2019,
                    "value": 38.0
                },
                {
                    "year": 2020,
                    "value": 46.0
                },
                {
                    "year": 2021,
                    "value": 26.0
                }
            ]
        },
        {
            "Alpha-3 code": "ARG",
            "Country or Area": "Argentina",
            "data": [
                {
                    "year": 2021,
                    "value": 438.0
                },
                {
                    "year": 2022,
                    "value": 324.0
                },
                {
                    "year": 2020,
                    "value": 432.0
                },
                {
                    "year": 2019,
                    "value": 290.0
                },
                {
                    "year": 2018,
                    "value": 281.0
                },
                {
                    "year": 2017,
                    "value": 330.0
                }
            ]
        },
        {
            "Alpha-3 code": "ATG",
            "Country or Area": "Antigua and Barbuda",
            "data": [
                {
                    "year": 2017,
                    "value": 0.0
                },
                {
                    "year": 2018,
                    "value": 2.0
                },
                {
                    "year": 2019,
                    "value": 0.0
                },
                {
                    "year": 2020,
                    "value": 0.0
                },
                {
                    "year": 2022,
                    "value": 1.0
                },
                {
                    "year": 2021,
                    "value": 5.0
                }
            ]
        },
        {
            "Alpha-3 code": "AUT",
            "Country or Area": "Austria",
            "data": [
                {
                    "year": 2021,
                    "value": 9.0
                },
                {
                    "year": 2022,
                    "value": 13.0
                },
                {
                    "year": 2020,
                    "value": 8.0
                },
                {
                    "year": 2019,
                    "value": 20.0
                },
                {
                    "year": 2018,
                    "value": 16.0
                },
                {
                    "year": 2017,
                    "value": 6.0
                },
                {
                    "year": 2010,
                    "value": 7.0
                },
                {
                    "year": 2011,
                    "value": 19.0
                },
                {
                    "year": 2012,
                    "value": 19.0
                },
                {
                    "year": 2013,
                    "value": 9.0
                },
                {
                    "year": 2014,
                    "value": 14.0
                },
                {
                    "year": 2015,
                    "value": 11.0
                },
                {
                    "year": 2016,
                    "value": 8.0
                }
            ]
        },
        {
            "Alpha-3 code": "BHS",
            "Country or Area": "Bahamas",
            "data": [
                {
                    "year": 2016,
                    "value": 14.0
                },
                {
                    "year": 2017,
                    "value": 15.0
                },
                {
                    "year": 2018,
                    "value": 26.0
                },
                {
                    "year": 2019,
                    "value": 36.0
                },
                {
                    "year": 2020,
                    "value": 15.0
                },
                {
                    "year": 2022,
                    "value": 18.0
                },
                {
                    "year": 2021,
                    "value": 22.0
                }
            ]
        },
        {
            "Alpha-3 code": "BIH",
            "Country or Area": "Bosnia and Herzegovina",
            "data": [
                {
                    "year": 2021,
                    "value": 6.0
                },
                {
                    "year": 2022,
                    "value": 5.0
                },
                {
                    "year": 2020,
                    "value": 8.0
                },
                {
                    "year": 2019,
                    "value": 6.0
                }
            ]
        },
        {
            "Alpha-3 code": "BLR",
            "Country or Area": "Belarus",
            "data": [
                {
                    "year": 2018,
                    "value": 90.0
                },
                {
                    "year": 2019,
                    "value": 90.0
                },
                {
                    "year": 2017,
                    "value": 109.0
                },
                {
                    "year": 2016,
                    "value": 152.0
                },
                {
                    "year": 2015,
                    "value": 133.0
                }
            ]
        },
        {
            "Alpha-3 code": "BLZ",
            "Country or Area": "Belize",
            "data": [
                {
                    "year": 2016,
                    "value": 0.0
                },
                {
                    "year": 2017,
                    "value": 1.0
                },
                {
                    "year": 2019,
                    "value": 0.0
                },
                {
                    "year": 2018,
                    "value": 0.0
                },
                {
                    "year": 2022,
                    "value": 0.0
                },
                {
                    "year": 2020,
                    "value": 1.0
                },
                {
                    "year": 2021,
                    "value": 0.0
                }
            ]
        },
        {
            "Alpha-3 code": "BOL",
            "Country or Area": "Bolivia",
            "data": [
                {
                    "year": 2020,
                    "value": 0.0
                },
                {
                    "year": 2021,
                    "value": 1.0
                },
                {
                    "year": 2022,
                    "value": 0.0
                },
                {
                    "year": 2018,
                    "value": 0.0
                },
                {
                    "year": 2019,
                    "value": 0.0
                }
            ]
        },
        {
            "Alpha-3 code": "BRB",
            "Country or Area": "Barbados",
            "data": [
                {
                    "year": 2019,
                    "value": 0.0
                },
                {
                    "year": 2017,
                    "value": 4.0
                },
                {
                    "year": 2018,
                    "value": 4.0
                },
                {
                    "year": 2016,
                    "value": 0.0
                },
                {
                    "year": 2021,
                    "value": 0.0
                },
                {
                    "year": 2022,
                    "value": 0.0
                },
                {
                    "year": 2020,
                    "value": 0.0
                }
            ]
        },
        {
            "Alpha-3 code": "BTN",
            "Country or Area": "Bhutan",
            "data": [
                {
                    "year": 2020,
                    "value": 13.0
                },
                {
                    "year": 2018,
                    "value": 2.0
                },
                {
                    "year": 2017,
                    "value": 5.0
                },
                {
                    "year": 2019,
                    "value": 5.0
                }
            ]
        },
        {
            "Alpha-3 code": "CAN",
            "Country or Area": "Canada",
            "data": [
                {
                    "year": 2019,
                    "value": 185.0
                },
                {
                    "year": 2018,
                    "value": 165.0
                },
                {
                    "year": 2017,
                    "value": 190.0
                },
                {
                    "year": 2016,
                    "value": 184.0
                },
                {
                    "year": 2015,
                    "value": 198.0
                },
                {
                    "year": 2014,
                    "value": 161.0
                },
                {
                    "year": 2013,
                    "value": 161.0
                },
                {
                    "year": 2020,
                    "value": 215.0
                },
                {
                    "year": 2022,
                    "value": 224.0
                },
                {
                    "year": 2021,
                    "value": 214.0
                }
            ]
        },
        {
            "Alpha-3 code": "CHE",
            "Country or Area": "Switzerland",
            "data": [
                {
                    "year": 2022,
                    "value": 5.0
                },
                {
                    "year": 2020,
                    "value": 6.0
                },
                {
                    "year": 2021,
                    "value": 2.0
                },
                {
                    "year": 2011,
                    "value": 12.0
                },
                {
                    "year": 2010,
                    "value": 6.0
                },
                {
                    "year": 2014,
                    "value": 6.0
                },
                {
                    "year": 2013,
                    "value": 12.0
                },
                {
                    "year": 2012,
                    "value": 8.0
                },
                {
                    "year": 2015,
                    "value": 6.0
                },
                {
                    "year": 2016,
                    "value": 11.0
                },
                {
                    "year": 2017,
                    "value": 11.0
                },
                {
                    "year": 2018,
                    "value": 12.0
                },
                {
                    "year": 2019,
                    "value": 5.0
                }
            ]
        },
        {
            "Alpha-3 code": "CHL",
            "Country or Area": "Chile",
            "data": [
                {
                    "year": 2019,
                    "value": 0.0
                },
                {
                    "year": 2018,
                    "value": 299.0
                },
                {
                    "year": 2017,
                    "value": 244.0
                },
                {
                    "year": 2016,
                    "value": 148.0
                },
                {
                    "year": 2020,
                    "value": 0.0
                },
                {
                    "year": 2021,
                    "value": 0.0
                },
                {
                    "year": 2022,
                    "value": 0.0
                }
            ]
        },
        {
            "Alpha-3 code": "COL",
            "Country or Area": "Colombia",
            "data": [
                {
                    "year": 2022,
                    "value": 4.0
                },
                {
                    "year": 2020,
                    "value": 8.0
                },
                {
                    "year": 2021,
                    "value": 3.0
                },
                {
                    "year": 2018,
                    "value": 2.0
                },
                {
                    "year": 2019,
                    "value": 10.0
                }
            ]
        },
        {
            "Alpha-3 code": "CRI",
            "Country or Area": "Costa Rica",
            "data": [
                {
                    "year": 2015,
                    "value": 357.0
                },
                {
                    "year": 2014,
                    "value": 261.0
                }
            ]
        },
        {
            "Alpha-3 code": "CZE",
            "Country or Area": "Czech Republic",
            "data": [
                {
                    "year": 2015,
                    "value": 16.0
                },
                {
                    "year": 2014,
                    "value": 15.0
                },
                {
                    "year": 2013,
                    "value": 15.0
                },
                {
                    "year": 2016,
                    "value": 4.0
                },
                {
                    "year": 2017,
                    "value": 14.0
                },
                {
                    "year": 2019,
                    "value": 17.0
                },
                {
                    "year": 2021,
                    "value": 11.0
                },
                {
                    "year": 2020,
                    "value": 8.0
                },
                {
                    "year": 2022,
                    "value": 18.0
                }
            ]
        },
        {
            "Alpha-3 code": "DEU",
            "Country or Area": "Germany",
            "data": [
                {
                    "year": 2020,
                    "value": 202.0
                },
                {
                    "year": 2021,
                    "value": 135.0
                },
                {
                    "year": 2019,
                    "value": 141.0
                },
                {
                    "year": 2018,
                    "value": 144.0
                },
                {
                    "year": 2017,
                    "value": 137.0
                },
                {
                    "year": 2016,
                    "value": 152.0
                },
                {
                    "year": 2014,
                    "value": 157.0
                },
                {
                    "year": 2015,
                    "value": 120.0
                }
            ]
        },
        {
            "Alpha-3 code": "DMA",
            "Country or Area": "Dominica",
            "data": [
                {
                    "year": 2015,
                    "value": 3.0
                },
                {
                    "year": 2014,
                    "value": 6.0
                },
                {
                    "year": 2016,
                    "value": 3.0
                },
                {
                    "year": 2017,
                    "value": 3.0
                },
                {
                    "year": 2018,
                    "value": 9.0
                },
                {
                    "year": 2019,
                    "value": 5.0
                },
                {
                    "year": 2021,
                    "value": 3.0
                },
                {
                    "year": 2020,
                    "value": 0.0
                }
            ]
        },
        {
            "Alpha-3 code": "DOM",
            "Country or Area": "Dominican Republic",
            "data": [
                {
                    "year": 2020,
                    "value": 203.0
                },
                {
                    "year": 2021,
                    "value": 216.0
                },
                {
                    "year": 2022,
                    "value": 237.0
                },
                {
                    "year": 2019,
                    "value": 182.0
                },
                {
                    "year": 2018,
                    "value": 108.0
                },
                {
                    "year": 2017,
                    "value": 179.0
                },
                {
                    "year": 2016,
                    "value": 239.0
                }
            ]
        },
        {
            "Alpha-3 code": "DZA",
            "Country or Area": "Algeria",
            "data": [
                {
                    "year": 2016,
                    "value": 243.0
                },
                {
                    "year": 2017,
                    "value": 252.0
                },
                {
                    "year": 2015,
                    "value": 241.0
                },
                {
                    "year": 2018,
                    "value": 247.0
                },
                {
                    "year": 2019,
                    "value": 251.0
                },
                {
                    "year": 2022,
                    "value": 474.0
                },
                {
                    "year": 2021,
                    "value": 317.0
                },
                {
                    "year": 2020,
                    "value": 299.0
                }
            ]
        },
        {
            "Alpha-3 code": "ECU",
            "Country or Area": "Ecuador",
            "data": [
                {
                    "year": 2020,
                    "value": 235.0
                },
                {
                    "year": 2021,
                    "value": 93.0
                },
                {
                    "year": 2022,
                    "value": 126.0
                },
                {
                    "year": 2019,
                    "value": 235.0
                },
                {
                    "year": 2018,
                    "value": 209.0
                },
                {
                    "year": 2015,
                    "value": 78.0
                },
                {
                    "year": 2014,
                    "value": 72.0
                },
                {
                    "year": 2017,
                    "value": 181.0
                },
                {
                    "year": 2016,
                    "value": 63.0
                }
            ]
        },
        {
            "Alpha-3 code": "ESP",
            "Country or Area": "Spain",
            "data": [
                {
                    "year": 2017,
                    "value": 23.0
                },
                {
                    "year": 2016,
                    "value": 34.0
                },
                {
                    "year": 2018,
                    "value": 18.0
                },
                {
                    "year": 2019,
                    "value": 21.0
                },
                {
                    "year": 2022,
                    "value": 35.0
                },
                {
                    "year": 2021,
                    "value": 36.0
                },
                {
                    "year": 2020,
                    "value": 24.0
                }
            ]
        },
        {
            "Alpha-3 code": "FIN",
            "Country or Area": "Finland",
            "data": [
                {
                    "year": 2019,
                    "value": 37.0
                },
                {
                    "year": 2018,
                    "value": 39.0
                },
                {
                    "year": 2016,
                    "value": 26.0
                },
                {
                    "year": 2017,
                    "value": 22.0
                },
                {
                    "year": 2013,
                    "value": 43.0
                },
                {
                    "year": 2015,
                    "value": 40.0
                },
                {
                    "year": 2014,
                    "value": 41.0
                }
            ]
        },
        {
            "Alpha-3 code": "GRC",
            "Country or Area": "Greece",
            "data": [
                {
                    "year": 2021,
                    "value": 14.0
                },
                {
                    "year": 2022,
                    "value": 39.0
                }
            ]
        },
        {
            "Alpha-3 code": "GRD",
            "Country or Area": "Grenada",
            "data": [
                {
                    "year": 2021,
                    "value": 2.0
                },
                {
                    "year": 2020,
                    "value": 7.0
                },
                {
                    "year": 2017,
                    "value": 3.0
                },
                {
                    "year": 2016,
                    "value": 3.0
                },
                {
                    "year": 2018,
                    "value": 9.0
                },
                {
                    "year": 2019,
                    "value": 12.0
                }
            ]
        },
        {
            "Alpha-3 code": "GTM",
            "Country or Area": "Guatemala",
            "data": [
                {
                    "year": 2019,
                    "value": 0.0
                },
                {
                    "year": 2018,
                    "value": 0.0
                },
                {
                    "year": 2017,
                    "value": 0.0
                },
                {
                    "year": 2020,
                    "value": 0.0
                },
                {
                    "year": 2021,
                    "value": 0.0
                }
            ]
        },
        {
            "Alpha-3 code": "GUY",
            "Country or Area": "Guyana",
            "data": [
                {
                    "year": 2021,
                    "value": 10.0
                },
                {
                    "year": 2017,
                    "value": 50.0
                },
                {
                    "year": 2016,
                    "value": 28.0
                },
                {
                    "year": 2018,
                    "value": 51.0
                },
                {
                    "year": 2019,
                    "value": 9.0
                },
                {
                    "year": 2020,
                    "value": 10.0
                }
            ]
        },
        {
            "Alpha-3 code": "HND",
            "Country or Area": "Honduras",
            "data": [
                {
                    "year": 2020,
                    "value": 6.0
                },
                {
                    "year": 2019,
                    "value": 6.0
                },
                {
                    "year": 2018,
                    "value": 29.0
                },
                {
                    "year": 2016,
                    "value": 91.0
                },
                {
                    "year": 2017,
                    "value": 84.0
                },
                {
                    "year": 2015,
                    "value": 124.0
                },
                {
                    "year": 2013,
                    "value": 6.0
                },
                {
                    "year": 2014,
                    "value": 7.0
                },
                {
                    "year": 2021,
                    "value": 9.0
                }
            ]
        },
        {
            "Alpha-3 code": "HRV",
            "Country or Area": "Croatia",
            "data": [
                {
                    "year": 2021,
                    "value": 2.0
                },
                {
                    "year": 2020,
                    "value": 13.0
                },
                {
                    "year": 2022,
                    "value": 4.0
                },
                {
                    "year": 2017,
                    "value": 0.0
                },
                {
                    "year": 2016,
                    "value": 0.0
                },
                {
                    "year": 2018,
                    "value": 2.0
                },
                {
                    "year": 2019,
                    "value": 8.0
                }
            ]
        },
        {
            "Alpha-3 code": "HUN",
            "Country or Area": "Hungary",
            "data": [
                {
                    "year": 2019,
                    "value": 14.0
                },
                {
                    "year": 2018,
                    "value": 8.0
                },
                {
                    "year": 2016,
                    "value": 19.0
                },
                {
                    "year": 2017,
                    "value": 24.0
                },
                {
                    "year": 2020,
                    "value": 32.0
                },
                {
                    "year": 2021,
                    "value": 30.0
                }
            ]
        },
        {
            "Alpha-3 code": "IRL",
            "Country or Area": "Ireland",
            "data": [
                {
                    "year": 2022,
                    "value": 7.0
                }
            ]
        },
        {
            "Alpha-3 code": "ISL",
            "Country or Area": "Iceland",
            "data": [
                {
                    "year": 2021,
                    "value": 1.0
                },
                {
                    "year": 2017,
                    "value": 0.0
                },
                {
                    "year": 2016,
                    "value": 0.0
                },
                {
                    "year": 2014,
                    "value": 0.0
                },
                {
                    "year": 2013,
                    "value": 1.0
                },
                {
                    "year": 2010,
                    "value": 1.0
                },
                {
                    "year": 2011,
                    "value": 1.0
                },
                {
                    "year": 2015,
                    "value": 2.0
                },
                {
                    "year": 2018,
                    "value": 1.0
                },
                {
                    "year": 2019,
                    "value": 1.0
                },
                {
                    "year": 2020,
                    "value": 1.0
                }
            ]
        },
        {
            "Alpha-3 code": "ITA",
            "Country or Area": "Italy",
            "data": [
                {
                    "year": 2020,
                    "value": 20.0
                },
                {
                    "year": 2019,
                    "value": 16.0
                },
                {
                    "year": 2018,
                    "value": 17.0
                },
                {
                    "year": 2016,
                    "value": 18.0
                },
                {
                    "year": 2017,
                    "value": 19.0
                },
                {
                    "year": 2021,
                    "value": 22.0
                },
                {
                    "year": 2022,
                    "value": 16.0
                }
            ]
        },
        {
            "Alpha-3 code": "JAM",
            "Country or Area": "Jamaica",
            "data": [
                {
                    "year": 2022,
                    "value": 18.0
                },
                {
                    "year": 2021,
                    "value": 36.0
                },
                {
                    "year": 2017,
                    "value": 67.0
                },
                {
                    "year": 2018,
                    "value": 69.0
                },
                {
                    "year": 2019,
                    "value": 38.0
                },
                {
                    "year": 2020,
                    "value": 14.0
                }
            ]
        },
        {
            "Alpha-3 code": "JOR",
            "Country or Area": "Jordan",
            "data": [
                {
                    "year": 2020,
                    "value": 21.0
                },
                {
                    "year": 2019,
                    "value": 2.0
                },
                {
                    "year": 2018,
                    "value": 2.0
                },
                {
                    "year": 2017,
                    "value": 86.0
                },
                {
                    "year": 2021,
                    "value": 13.0
                },
                {
                    "year": 2022,
                    "value": 21.0
                }
            ]
        },
        {
            "Alpha-3 code": "KNA",
            "Country or Area": "Saint Kitts and Nevis",
            "data": [
                {
                    "year": 2021,
                    "value": 6.0
                },
                {
                    "year": 2017,
                    "value": 5.0
                },
                {
                    "year": 2016,
                    "value": 0.0
                },
                {
                    "year": 2018,
                    "value": 2.0
                },
                {
                    "year": 2019,
                    "value": 1.0
                },
                {
                    "year": 2020,
                    "value": 4.0
                }
            ]
        },
        {
            "Alpha-3 code": "LCA",
            "Country or Area": "Saint Lucia",
            "data": [
                {
                    "year": 2020,
                    "value": 0.0
                },
                {
                    "year": 2019,
                    "value": 2.0
                },
                {
                    "year": 2018,
                    "value": 0.0
                },
                {
                    "year": 2017,
                    "value": 7.0
                },
                {
                    "year": 2021,
                    "value": 0.0
                },
                {
                    "year": 2022,
                    "value": 2.0
                }
            ]
        },
        {
            "Alpha-3 code": "LIE",
            "Country or Area": "Liechtenstein",
            "data": [
                {
                    "year": 2016,
                    "value": 0.0
                }
            ]
        },
        {
            "Alpha-3 code": "LTU",
            "Country or Area": "Lithuania",
            "data": [
                {
                    "year": 2016,
                    "value": 19.0
                },
                {
                    "year": 2017,
                    "value": 12.0
                },
                {
                    "year": 2015,
                    "value": 21.0
                },
                {
                    "year": 2013,
                    "value": 32.0
                },
                {
                    "year": 2014,
                    "value": 28.0
                },
                {
                    "year": 2018,
                    "value": 26.0
                },
                {
                    "year": 2019,
                    "value": 31.0
                },
                {
                    "year": 2022,
                    "value": 20.0
                },
                {
                    "year": 2021,
                    "value": 31.0
                },
                {
                    "year": 2020,
                    "value": 22.0
                }
            ]
        },
        {
            "Alpha-3 code": "LVA",
            "Country or Area": "Latvia",
            "data": [
                {
                    "year": 2021,
                    "value": 7.0
                },
                {
                    "year": 2022,
                    "value": 5.0
                },
                {
                    "year": 2019,
                    "value": 10.0
                },
                {
                    "year": 2020,
                    "value": 8.0
                },
                {
                    "year": 2018,
                    "value": 8.0
                },
                {
                    "year": 2017,
                    "value": 15.0
                },
                {
                    "year": 2016,
                    "value": 2.0
                }
            ]
        },
        {
            "Alpha-3 code": "MAC",
            "Country or Area": "Macau",
            "data": [
                {
                    "year": 2016,
                    "value": 1.0
                },
                {
                    "year": 2012,
                    "value": 1.0
                },
                {
                    "year": 2011,
                    "value": 1.0
                },
                {
                    "year": 2010,
                    "value": 2.0
                }
            ]
        },
        {
            "Alpha-3 code": "MAR",
            "Country or Area": "Morocco",
            "data": [
                {
                    "year": 2016,
                    "value": 113.0
                },
                {
                    "year": 2017,
                    "value": 431.0
                },
                {
                    "year": 2018,
                    "value": 291.0
                },
                {
                    "year": 2020,
                    "value": 65.0
                },
                {
                    "year": 2019,
                    "value": 142.0
                },
                {
                    "year": 2022,
                    "value": 139.0
                },
                {
                    "year": 2021,
                    "value": 217.0
                }
            ]
        },
        {
            "Alpha-3 code": "MDA",
            "Country or Area": "Moldova",
            "data": [
                {
                    "year": 2020,
                    "value": 23.0
                },
                {
                    "year": 2019,
                    "value": 21.0
                },
                {
                    "year": 2018,
                    "value": 24.0
                },
                {
                    "year": 2017,
                    "value": 14.0
                },
                {
                    "year": 2016,
                    "value": 18.0
                },
                {
                    "year": 2015,
                    "value": 16.0
                }
            ]
        },
        {
            "Alpha-3 code": "MEX",
            "Country or Area": "Mexico",
            "data": [
                {
                    "year": 2015,
                    "value": 24.0
                },
                {
                    "year": 2016,
                    "value": 33.0
                },
                {
                    "year": 2017,
                    "value": 40.0
                },
                {
                    "year": 2018,
                    "value": 15.0
                },
                {
                    "year": 2019,
                    "value": 11.0
                },
                {
                    "year": 2020,
                    "value": 12.0
                },
                {
                    "year": 2021,
                    "value": 5.0
                },
                {
                    "year": 2022,
                    "value": 12.0
                }
            ]
        },
        {
            "Alpha-3 code": "MKD",
            "Country or Area": "Macedonia",
            "data": [
                {
                    "year": 2022,
                    "value": 9.0
                },
                {
                    "year": 2021,
                    "value": 6.0
                },
                {
                    "year": 2020,
                    "value": 2.0
                },
                {
                    "year": 2019,
                    "value": 14.0
                }
            ]
        },
        {
            "Alpha-3 code": "MLT",
            "Country or Area": "Malta",
            "data": [
                {
                    "year": 2018,
                    "value": 3.0
                },
                {
                    "year": 2020,
                    "value": 3.0
                },
                {
                    "year": 2019,
                    "value": 0.0
                },
                {
                    "year": 2017,
                    "value": 1.0
                },
                {
                    "year": 2016,
                    "value": 0.0
                },
                {
                    "year": 2015,
                    "value": 0.0
                },
                {
                    "year": 2021,
                    "value": 1.0
                }
            ]
        },
        {
            "Alpha-3 code": "MNE",
            "Country or Area": "Montenegro",
            "data": [
                {
                    "year": 2021,
                    "value": 1.0
                },
                {
                    "year": 2022,
                    "value": 5.0
                },
                {
                    "year": 2016,
                    "value": 9.0
                },
                {
                    "year": 2017,
                    "value": 4.0
                },
                {
                    "year": 2019,
                    "value": 10.0
                },
                {
                    "year": 2020,
                    "value": 4.0
                },
                {
                    "year": 2018,
                    "value": 4.0
                }
            ]
        },
        {
            "Alpha-3 code": "MNG",
            "Country or Area": "Mongolia",
            "data": [
                {
                    "year": 2018,
                    "value": 40.0
                },
                {
                    "year": 2020,
                    "value": 46.0
                },
                {
                    "year": 2019,
                    "value": 47.0
                },
                {
                    "year": 2017,
                    "value": 28.0
                },
                {
                    "year": 2016,
                    "value": 25.0
                },
                {
                    "year": 2015,
                    "value": 21.0
                },
                {
                    "year": 2013,
                    "value": 14.0
                },
                {
                    "year": 2014,
                    "value": 26.0
                },
                {
                    "year": 2021,
                    "value": 56.0
                }
            ]
        },
        {
            "Alpha-3 code": "MUS",
            "Country or Area": "Mauritius",
            "data": [
                {
                    "year": 2022,
                    "value": 12.0
                }
            ]
        },
        {
            "Alpha-3 code": "NIC",
            "Country or Area": "Nicaragua",
            "data": [
                {
                    "year": 2016,
                    "value": 12.0
                },
                {
                    "year": 2017,
                    "value": 17.0
                },
                {
                    "year": 2018,
                    "value": 12.0
                },
                {
                    "year": 2019,
                    "value": 23.0
                }
            ]
        },
        {
            "Alpha-3 code": "NLD",
            "Country or Area": "Netherlands",
            "data": [
                {
                    "year": 2019,
                    "value": 27.0
                },
                {
                    "year": 2018,
                    "value": 23.0
                },
                {
                    "year": 2020,
                    "value": 31.0
                },
                {
                    "year": 2017,
                    "value": 14.0
                },
                {
                    "year": 2016,
                    "value": 17.0
                },
                {
                    "year": 2014,
                    "value": 22.0
                },
                {
                    "year": 2013,
                    "value": 21.0
                },
                {
                    "year": 2015,
                    "value": 17.0
                },
                {
                    "year": 2022,
                    "value": 32.0
                },
                {
                    "year": 2021,
                    "value": 25.0
                }
            ]
        },
        {
            "Alpha-3 code": "OMN",
            "Country or Area": "Oman",
            "data": [
                {
                    "year": 2021,
                    "value": 6.0
                },
                {
                    "year": 2022,
                    "value": 5.0
                },
                {
                    "year": 2015,
                    "value": 7.0
                },
                {
                    "year": 2016,
                    "value": 8.0
                },
                {
                    "year": 2017,
                    "value": 6.0
                },
                {
                    "year": 2020,
                    "value": 9.0
                },
                {
                    "year": 2018,
                    "value": 10.0
                },
                {
                    "year": 2019,
                    "value": 17.0
                }
            ]
        },
        {
            "Alpha-3 code": "PAN",
            "Country or Area": "Panama",
            "data": [
                {
                    "year": 2018,
                    "value": 66.0
                },
                {
                    "year": 2020,
                    "value": 0.0
                },
                {
                    "year": 2019,
                    "value": 62.0
                },
                {
                    "year": 2017,
                    "value": 65.0
                },
                {
                    "year": 2022,
                    "value": 0.0
                },
                {
                    "year": 2021,
                    "value": 0.0
                }
            ]
        },
        {
            "Alpha-3 code": "PER",
            "Country or Area": "Peru",
            "data": [
                {
                    "year": 2016,
                    "value": 366.0
                },
                {
                    "year": 2020,
                    "value": 35.0
                },
                {
                    "year": 2018,
                    "value": 187.0
                },
                {
                    "year": 2019,
                    "value": 53.0
                }
            ]
        },
        {
            "Alpha-3 code": "PHL",
            "Country or Area": "Philippines",
            "data": [
                {
                    "year": 2019,
                    "value": 89.0
                },
                {
                    "year": 2018,
                    "value": 109.0
                },
                {
                    "year": 2017,
                    "value": 109.0
                },
                {
                    "year": 2016,
                    "value": 126.0
                }
            ]
        },
        {
            "Alpha-3 code": "PRY",
            "Country or Area": "Paraguay",
            "data": [
                {
                    "year": 2016,
                    "value": 274.0
                },
                {
                    "year": 2017,
                    "value": 99.0
                },
                {
                    "year": 2018,
                    "value": 118.0
                }
            ]
        },
        {
            "Alpha-3 code": "PSE",
            "Country or Area": "Palestine",
            "data": [
                {
                    "year": 2018,
                    "value": 10.0
                }
            ]
        },
        {
            "Alpha-3 code": "QAT",
            "Country or Area": "Qatar",
            "data": [
                {
                    "year": 2021,
                    "value": 4.0
                }
            ]
        },
        {
            "Alpha-3 code": "RUS",
            "Country or Area": "Russian Federation",
            "data": [
                {
                    "year": 2021,
                    "value": 3645.0
                },
                {
                    "year": 2018,
                    "value": 3264.0
                },
                {
                    "year": 2019,
                    "value": 3301.0
                },
                {
                    "year": 2020,
                    "value": 3735.0
                },
                {
                    "year": 2017,
                    "value": 2886.0
                },
                {
                    "year": 2016,
                    "value": 3208.0
                },
                {
                    "year": 2015,
                    "value": 3054.0
                },
                {
                    "year": 2010,
                    "value": 2083.0
                },
                {
                    "year": 2011,
                    "value": 2062.0
                },
                {
                    "year": 2014,
                    "value": 2825.0
                }
            ]
        },
        {
            "Alpha-3 code": "SLV",
            "Country or Area": "El Salvador",
            "data": [
                {
                    "year": 2016,
                    "value": 1.0
                },
                {
                    "year": 2017,
                    "value": 2.0
                },
                {
                    "year": 2020,
                    "value": 0.0
                },
                {
                    "year": 2019,
                    "value": 0.0
                },
                {
                    "year": 2018,
                    "value": 0.0
                },
                {
                    "year": 2021,
                    "value": 3.0
                },
                {
                    "year": 2022,
                    "value": 1.0
                }
            ]
        },
        {
            "Alpha-3 code": "SUR",
            "Country or Area": "Suriname",
            "data": [
                {
                    "year": 2022,
                    "value": 17.0
                },
                {
                    "year": 2021,
                    "value": 9.0
                },
                {
                    "year": 2018,
                    "value": 9.0
                },
                {
                    "year": 2019,
                    "value": 7.0
                },
                {
                    "year": 2020,
                    "value": 16.0
                },
                {
                    "year": 2017,
                    "value": 6.0
                },
                {
                    "year": 2016,
                    "value": 15.0
                }
            ]
        },
        {
            "Alpha-3 code": "SVN",
            "Country or Area": "Slovenia",
            "data": [
                {
                    "year": 2020,
                    "value": 2.0
                },
                {
                    "year": 2019,
                    "value": 2.0
                },
                {
                    "year": 2018,
                    "value": 2.0
                },
                {
                    "year": 2021,
                    "value": 1.0
                }
            ]
        },
        {
            "Alpha-3 code": "SWZ",
            "Country or Area": "Swaziland",
            "data": [
                {
                    "year": 2021,
                    "value": 6.0
                }
            ]
        },
        {
            "Alpha-3 code": "TJK",
            "Country or Area": "Tajikistan",
            "data": [
                {
                    "year": 2020,
                    "value": 2.0
                }
            ]
        },
        {
            "Alpha-3 code": "TTO",
            "Country or Area": "Trinidad and Tobago",
            "data": [
                {
                    "year": 2020,
                    "value": 2.0
                },
                {
                    "year": 2018,
                    "value": 4.0
                },
                {
                    "year": 2019,
                    "value": 6.0
                },
                {
                    "year": 2017,
                    "value": 7.0
                }
            ]
        },
        {
            "Alpha-3 code": "URY",
            "Country or Area": "Uruguay",
            "data": [
                {
                    "year": 2017,
                    "value": 89.0
                },
                {
                    "year": 2016,
                    "value": 98.0
                },
                {
                    "year": 2015,
                    "value": 99.0
                },
                {
                    "year": 2019,
                    "value": 62.0
                },
                {
                    "year": 2018,
                    "value": 137.0
                },
                {
                    "year": 2020,
                    "value": 77.0
                },
                {
                    "year": 2021,
                    "value": 69.0
                },
                {
                    "year": 2022,
                    "value": 96.0
                }
            ]
        },
        {
            "Alpha-3 code": "USA",
            "Country or Area": "USA",
            "data": [
                {
                    "year": 2021,
                    "value": 7143.07200660736
                }
            ]
        },
        {
            "Alpha-3 code": "VAT",
            "Country or Area": "Holy See",
            "data": [
                {
                    "year": 2021,
                    "value": 0.0
                },
                {
                    "year": 2022,
                    "value": 0.0
                }
            ]
        },
        {
            "Alpha-3 code": "VCT",
            "Country or Area": "Saint Vincent and the Grenadines",
            "data": [
                {
                    "year": 2022,
                    "value": 8.0
                },
                {
                    "year": 2021,
                    "value": 8.0
                },
                {
                    "year": 2020,
                    "value": 9.0
                },
                {
                    "year": 2018,
                    "value": 6.0
                },
                {
                    "year": 2019,
                    "value": 9.0
                }
            ]
        }
    ]
}